{
  "generated_at": "2026-05-10T11:00:35.891948",
  "cohort_rebalanced_at": "2026-05-05",
  "index_score": 0.157385,
  "leverage_dampening": false,
  "cohort_stats": {
    "total_equity": 555826615.59,
    "total_wallets": 100,
    "active_wallets": 100,
    "gross_long_usd": 894208629.07,
    "gross_short_usd": 634662109.03,
    "net_usd": 259546520.04,
    "gross_notional_usd": 1528870738.1,
    "L_cohort_total": 2.7506
  },
  "assets": [
    {
      "asset": "BTC",
      "long_usd": 315034694.29,
      "short_usd": 106398987.07,
      "net_usd": 208635707.22,
      "tilt": 0.4951,
      "position_count": 41,
      "long_count": 21,
      "short_count": 20,
      "L_net_margin": 4.656644,
      "L_net_equity": 0.375361,
      "conv_equity": 0.3566,
      "free": true
    },
    {
      "asset": "ETH",
      "long_usd": 286390192.05,
      "short_usd": 89338662.42,
      "net_usd": 197051529.63,
      "tilt": 0.5245,
      "position_count": 37,
      "long_count": 14,
      "short_count": 23,
      "L_net_margin": 8.169776,
      "L_net_equity": 0.35452,
      "conv_equity": 0.3875,
      "free": true
    },
    {
      "asset": "HYPE",
      "long_usd": 95840659.05,
      "short_usd": 196664029.7,
      "net_usd": -100823370.65,
      "tilt": -0.3447,
      "position_count": 43,
      "long_count": 11,
      "short_count": 32,
      "L_net_margin": -1.850832,
      "L_net_equity": -0.181394,
      "conv_equity": -0.2554,
      "free": true
    },
    {
      "asset": "SOL",
      "long_usd": 66548017.77,
      "short_usd": 31156516.79,
      "net_usd": 35391500.98,
      "tilt": 0.3622,
      "position_count": 27,
      "long_count": 14,
      "short_count": 13,
      "L_net_margin": 3.530489,
      "L_net_equity": 0.063674,
      "conv_equity": 0.5196,
      "free": true
    },
    {
      "asset": "ZEC",
      "long_usd": 13202201.78,
      "short_usd": 45530978.55,
      "net_usd": -32328776.76,
      "tilt": -0.5504,
      "position_count": 18,
      "long_count": 5,
      "short_count": 13,
      "L_net_margin": -1.568751,
      "L_net_equity": -0.058163,
      "conv_equity": -0.4064,
      "free": true
    },
    {
      "asset": "TON",
      "long_usd": 7163735.64,
      "short_usd": 15296001.84,
      "net_usd": -8132266.2,
      "tilt": -0.3621,
      "position_count": 14,
      "long_count": 2,
      "short_count": 12,
      "L_net_margin": -1.173963,
      "L_net_equity": -0.014631,
      "conv_equity": -0.4039,
      "free": false
    },
    {
      "asset": "LIT",
      "long_usd": 4831609.95,
      "short_usd": 10871833.21,
      "net_usd": -6040223.26,
      "tilt": -0.3846,
      "position_count": 16,
      "long_count": 7,
      "short_count": 9,
      "L_net_margin": -0.788869,
      "L_net_equity": -0.010867,
      "conv_equity": -0.257,
      "free": false
    },
    {
      "asset": "DOGE",
      "long_usd": 1447485.58,
      "short_usd": 6712175.77,
      "net_usd": -5264690.19,
      "tilt": -0.6452,
      "position_count": 9,
      "long_count": 2,
      "short_count": 7,
      "L_net_margin": -6.452094,
      "L_net_equity": -0.009472,
      "conv_equity": -0.6106,
      "free": false
    },
    {
      "asset": "AAVE",
      "long_usd": 7589546.02,
      "short_usd": 12632355.17,
      "net_usd": -5042809.14,
      "tilt": -0.2494,
      "position_count": 11,
      "long_count": 4,
      "short_count": 7,
      "L_net_margin": -2.098432,
      "L_net_equity": -0.009073,
      "conv_equity": 0.0567,
      "free": false
    },
    {
      "asset": "ASTER",
      "long_usd": 2129649.07,
      "short_usd": 6968434.31,
      "net_usd": -4838785.24,
      "tilt": -0.5318,
      "position_count": 9,
      "long_count": 2,
      "short_count": 7,
      "L_net_margin": -1.797912,
      "L_net_equity": -0.008706,
      "conv_equity": -0.6185,
      "free": false
    },
    {
      "asset": "SUI",
      "long_usd": 76893.16,
      "short_usd": 4571829.4,
      "net_usd": -4494936.24,
      "tilt": -0.9669,
      "position_count": 8,
      "long_count": 3,
      "short_count": 5,
      "L_net_margin": -9.669186,
      "L_net_equity": -0.008087,
      "conv_equity": -0.9624,
      "free": false
    },
    {
      "asset": "PAXG",
      "long_usd": 8153707.77,
      "short_usd": 3750097.91,
      "net_usd": 4403609.86,
      "tilt": 0.3699,
      "position_count": 9,
      "long_count": 3,
      "short_count": 6,
      "L_net_margin": 1.87469,
      "L_net_equity": 0.007923,
      "conv_equity": 0.2388,
      "free": false
    },
    {
      "asset": "XPL",
      "long_usd": 775822.7,
      "short_usd": 4997697.77,
      "net_usd": -4221875.07,
      "tilt": -0.7312,
      "position_count": 14,
      "long_count": 3,
      "short_count": 11,
      "L_net_margin": -4.389854,
      "L_net_equity": -0.007596,
      "conv_equity": -0.5219,
      "free": false
    },
    {
      "asset": "FARTCOIN",
      "long_usd": 2950706.03,
      "short_usd": 6920611.96,
      "net_usd": -3969905.93,
      "tilt": -0.4022,
      "position_count": 13,
      "long_count": 3,
      "short_count": 10,
      "L_net_margin": -2.473198,
      "L_net_equity": -0.007142,
      "conv_equity": -0.5261,
      "free": false
    },
    {
      "asset": "VVV",
      "long_usd": 1938129.92,
      "short_usd": 5817535.42,
      "net_usd": -3879405.49,
      "tilt": -0.5002,
      "position_count": 9,
      "long_count": 3,
      "short_count": 6,
      "L_net_margin": -1.500608,
      "L_net_equity": -0.00698,
      "conv_equity": -0.1019,
      "free": false
    },
    {
      "asset": "MON",
      "long_usd": 7369572.07,
      "short_usd": 3523021.4,
      "net_usd": 3846550.67,
      "tilt": 0.3531,
      "position_count": 11,
      "long_count": 2,
      "short_count": 9,
      "L_net_margin": 1.630577,
      "L_net_equity": 0.00692,
      "conv_equity": 0.5616,
      "free": false
    },
    {
      "asset": "BNB",
      "long_usd": 0.0,
      "short_usd": 3660998.18,
      "net_usd": -3660998.18,
      "tilt": -1.0,
      "position_count": 6,
      "long_count": 0,
      "short_count": 6,
      "L_net_margin": -5.256467,
      "L_net_equity": -0.006587,
      "conv_equity": -1.0,
      "free": false
    },
    {
      "asset": "XRP",
      "long_usd": 3299541.14,
      "short_usd": 6796709.15,
      "net_usd": -3497168.01,
      "tilt": -0.3464,
      "position_count": 12,
      "long_count": 6,
      "short_count": 6,
      "L_net_margin": -5.031405,
      "L_net_equity": -0.006292,
      "conv_equity": -0.2275,
      "free": false
    },
    {
      "asset": "CHIP",
      "long_usd": 5338.89,
      "short_usd": 3160788.07,
      "net_usd": -3155449.18,
      "tilt": -0.9966,
      "position_count": 8,
      "long_count": 1,
      "short_count": 7,
      "L_net_margin": -2.989882,
      "L_net_equity": -0.005677,
      "conv_equity": -0.9987,
      "free": false
    },
    {
      "asset": "TAO",
      "long_usd": 4271820.82,
      "short_usd": 7338844.09,
      "net_usd": -3067023.28,
      "tilt": -0.2642,
      "position_count": 13,
      "long_count": 4,
      "short_count": 9,
      "L_net_margin": -1.320778,
      "L_net_equity": -0.005518,
      "conv_equity": -0.2991,
      "free": false
    },
    {
      "asset": "AVAX",
      "long_usd": 3061683.35,
      "short_usd": 705957.17,
      "net_usd": 2355726.19,
      "tilt": 0.6253,
      "position_count": 7,
      "long_count": 1,
      "short_count": 6,
      "L_net_margin": 6.244665,
      "L_net_equity": 0.004238,
      "conv_equity": 0.2646,
      "free": false
    },
    {
      "asset": "NEAR",
      "long_usd": 4947111.91,
      "short_usd": 7126961.14,
      "net_usd": -2179849.22,
      "tilt": -0.1805,
      "position_count": 14,
      "long_count": 6,
      "short_count": 8,
      "L_net_margin": -1.73891,
      "L_net_equity": -0.003922,
      "conv_equity": -0.1402,
      "free": false
    },
    {
      "asset": "UNI",
      "long_usd": 0.0,
      "short_usd": 1477878.47,
      "net_usd": -1477878.47,
      "tilt": -1.0,
      "position_count": 6,
      "long_count": 0,
      "short_count": 6,
      "L_net_margin": -10.0,
      "L_net_equity": -0.002659,
      "conv_equity": -1.0,
      "free": false
    },
    {
      "asset": "PENDLE",
      "long_usd": 0.0,
      "short_usd": 1382845.98,
      "net_usd": -1382845.98,
      "tilt": -1.0,
      "position_count": 5,
      "long_count": 0,
      "short_count": 5,
      "L_net_margin": -4.72451,
      "L_net_equity": -0.002488,
      "conv_equity": -1.0,
      "free": false
    },
    {
      "asset": "CFX",
      "long_usd": 1365739.33,
      "short_usd": 0.0,
      "net_usd": 1365739.33,
      "tilt": 1.0,
      "position_count": 1,
      "long_count": 1,
      "short_count": 0,
      "L_net_margin": 5.0,
      "L_net_equity": 0.002457,
      "conv_equity": 1.0,
      "free": false
    },
    {
      "asset": "ENA",
      "long_usd": 7324833.72,
      "short_usd": 5961727.79,
      "net_usd": 1363105.93,
      "tilt": 0.1026,
      "position_count": 19,
      "long_count": 8,
      "short_count": 11,
      "L_net_margin": 0.472993,
      "L_net_equity": 0.002452,
      "conv_equity": 0.2512,
      "free": false
    },
    {
      "asset": "KBONK",
      "long_usd": 2194028.78,
      "short_usd": 947400.85,
      "net_usd": 1246627.93,
      "tilt": 0.3968,
      "position_count": 6,
      "long_count": 1,
      "short_count": 5,
      "L_net_margin": 3.968346,
      "L_net_equity": 0.002243,
      "conv_equity": 0.3034,
      "free": false
    },
    {
      "asset": "PENGU",
      "long_usd": 0.0,
      "short_usd": 1230382.86,
      "net_usd": -1230382.86,
      "tilt": -1.0,
      "position_count": 6,
      "long_count": 0,
      "short_count": 6,
      "L_net_margin": -5.0,
      "L_net_equity": -0.002214,
      "conv_equity": -1.0,
      "free": false
    },
    {
      "asset": "LINEA",
      "long_usd": 1214536.22,
      "short_usd": 0.0,
      "net_usd": 1214536.22,
      "tilt": 1.0,
      "position_count": 1,
      "long_count": 1,
      "short_count": 0,
      "L_net_margin": 3.0,
      "L_net_equity": 0.002185,
      "conv_equity": 1.0,
      "free": false
    },
    {
      "asset": "MEGA",
      "long_usd": 1339941.06,
      "short_usd": 2474968.18,
      "net_usd": -1135027.11,
      "tilt": -0.2975,
      "position_count": 9,
      "long_count": 5,
      "short_count": 4,
      "L_net_margin": -0.827087,
      "L_net_equity": -0.002042,
      "conv_equity": -0.1068,
      "free": false
    },
    {
      "asset": "KPEPE",
      "long_usd": 3996001.73,
      "short_usd": 2913934.76,
      "net_usd": 1082066.97,
      "tilt": 0.1566,
      "position_count": 5,
      "long_count": 2,
      "short_count": 3,
      "L_net_margin": 1.565958,
      "L_net_equity": 0.001947,
      "conv_equity": 0.4013,
      "free": false
    },
    {
      "asset": "MNT",
      "long_usd": 1518570.61,
      "short_usd": 447978.4,
      "net_usd": 1070592.21,
      "tilt": 0.5444,
      "position_count": 6,
      "long_count": 2,
      "short_count": 4,
      "L_net_margin": 2.722007,
      "L_net_equity": 0.001926,
      "conv_equity": 0.0482,
      "free": false
    },
    {
      "asset": "TST",
      "long_usd": 1861689.46,
      "short_usd": 810458.83,
      "net_usd": 1051230.63,
      "tilt": 0.3934,
      "position_count": 5,
      "long_count": 3,
      "short_count": 2,
      "L_net_margin": 1.180208,
      "L_net_equity": 0.001891,
      "conv_equity": 0.8089,
      "free": false
    },
    {
      "asset": "ENS",
      "long_usd": 1014420.05,
      "short_usd": 0.0,
      "net_usd": 1014420.05,
      "tilt": 1.0,
      "position_count": 1,
      "long_count": 1,
      "short_count": 0,
      "L_net_margin": 5.0,
      "L_net_equity": 0.001825,
      "conv_equity": 1.0,
      "free": false
    },
    {
      "asset": "LTC",
      "long_usd": 2056817.46,
      "short_usd": 1053707.94,
      "net_usd": 1003109.53,
      "tilt": 0.3225,
      "position_count": 3,
      "long_count": 1,
      "short_count": 2,
      "L_net_margin": 3.224888,
      "L_net_equity": 0.001805,
      "conv_equity": 0.4408,
      "free": false
    },
    {
      "asset": "PUMP",
      "long_usd": 3158366.4,
      "short_usd": 4118928.62,
      "net_usd": -960562.22,
      "tilt": -0.132,
      "position_count": 14,
      "long_count": 5,
      "short_count": 9,
      "L_net_margin": -0.531329,
      "L_net_equity": -0.001728,
      "conv_equity": 0.1169,
      "free": false
    },
    {
      "asset": "HBAR",
      "long_usd": 943537.95,
      "short_usd": 0.0,
      "net_usd": 943537.95,
      "tilt": 1.0,
      "position_count": 1,
      "long_count": 1,
      "short_count": 0,
      "L_net_margin": 5.0,
      "L_net_equity": 0.001698,
      "conv_equity": 1.0,
      "free": false
    },
    {
      "asset": "PURR",
      "long_usd": 8.52,
      "short_usd": 939411.28,
      "net_usd": -939402.76,
      "tilt": -1.0,
      "position_count": 5,
      "long_count": 1,
      "short_count": 4,
      "L_net_margin": -2.999946,
      "L_net_equity": -0.00169,
      "conv_equity": -1.0,
      "free": false
    },
    {
      "asset": "WLFI",
      "long_usd": 399403.9,
      "short_usd": 1299935.34,
      "net_usd": -900531.44,
      "tilt": -0.5299,
      "position_count": 6,
      "long_count": 1,
      "short_count": 5,
      "L_net_margin": -1.183987,
      "L_net_equity": -0.00162,
      "conv_equity": -0.7586,
      "free": false
    },
    {
      "asset": "IP",
      "long_usd": 64.42,
      "short_usd": 835079.03,
      "net_usd": -835014.62,
      "tilt": -0.9998,
      "position_count": 4,
      "long_count": 1,
      "short_count": 3,
      "L_net_margin": -2.999537,
      "L_net_equity": -0.001502,
      "conv_equity": -0.9999,
      "free": false
    },
    {
      "asset": "DYDX",
      "long_usd": 780298.01,
      "short_usd": 0.0,
      "net_usd": 780298.01,
      "tilt": 1.0,
      "position_count": 1,
      "long_count": 1,
      "short_count": 0,
      "L_net_margin": 5.0,
      "L_net_equity": 0.001404,
      "conv_equity": 1.0,
      "free": false
    },
    {
      "asset": "SPX",
      "long_usd": 0.0,
      "short_usd": 720626.04,
      "net_usd": -720626.04,
      "tilt": -1.0,
      "position_count": 4,
      "long_count": 0,
      "short_count": 4,
      "L_net_margin": -5.0,
      "L_net_equity": -0.001296,
      "conv_equity": -1.0,
      "free": false
    },
    {
      "asset": "TIA",
      "long_usd": 0.0,
      "short_usd": 634313.72,
      "net_usd": -634313.72,
      "tilt": -1.0,
      "position_count": 5,
      "long_count": 0,
      "short_count": 5,
      "L_net_margin": -4.971221,
      "L_net_equity": -0.001141,
      "conv_equity": -1.0,
      "free": false
    },
    {
      "asset": "ADA",
      "long_usd": 1056292.02,
      "short_usd": 461700.47,
      "net_usd": 594591.55,
      "tilt": 0.3917,
      "position_count": 4,
      "long_count": 2,
      "short_count": 2,
      "L_net_margin": 3.91696,
      "L_net_equity": 0.00107,
      "conv_equity": 0.2112,
      "free": false
    },
    {
      "asset": "WIF",
      "long_usd": 1431527.61,
      "short_usd": 861379.25,
      "net_usd": 570148.36,
      "tilt": 0.2487,
      "position_count": 5,
      "long_count": 2,
      "short_count": 3,
      "L_net_margin": 1.243287,
      "L_net_equity": 0.001026,
      "conv_equity": 0.2083,
      "free": false
    },
    {
      "asset": "JUP",
      "long_usd": 946230.97,
      "short_usd": 385980.41,
      "net_usd": 560250.56,
      "tilt": 0.4205,
      "position_count": 4,
      "long_count": 2,
      "short_count": 2,
      "L_net_margin": 3.131987,
      "L_net_equity": 0.001008,
      "conv_equity": 0.0808,
      "free": false
    },
    {
      "asset": "APT",
      "long_usd": 162021.65,
      "short_usd": 706362.89,
      "net_usd": -544341.25,
      "tilt": -0.6268,
      "position_count": 3,
      "long_count": 1,
      "short_count": 2,
      "L_net_margin": -6.268435,
      "L_net_equity": -0.000979,
      "conv_equity": -0.8566,
      "free": false
    },
    {
      "asset": "MET",
      "long_usd": 0.0,
      "short_usd": 502676.42,
      "net_usd": -502676.42,
      "tilt": -1.0,
      "position_count": 3,
      "long_count": 0,
      "short_count": 3,
      "L_net_margin": -3.0,
      "L_net_equity": -0.000904,
      "conv_equity": -1.0,
      "free": false
    },
    {
      "asset": "POPCAT",
      "long_usd": 931307.0,
      "short_usd": 451909.41,
      "net_usd": 479397.59,
      "tilt": 0.3466,
      "position_count": 3,
      "long_count": 1,
      "short_count": 2,
      "L_net_margin": 1.039745,
      "L_net_equity": 0.000862,
      "conv_equity": 0.4633,
      "free": false
    },
    {
      "asset": "APEX",
      "long_usd": 861889.07,
      "short_usd": 421804.25,
      "net_usd": 440084.82,
      "tilt": 0.3428,
      "position_count": 3,
      "long_count": 1,
      "short_count": 2,
      "L_net_margin": 1.028481,
      "L_net_equity": 0.000792,
      "conv_equity": 0.2319,
      "free": false
    },
    {
      "asset": "TRX",
      "long_usd": 712607.55,
      "short_usd": 286658.23,
      "net_usd": 425949.32,
      "tilt": 0.4263,
      "position_count": 4,
      "long_count": 2,
      "short_count": 2,
      "L_net_margin": 4.262623,
      "L_net_equity": 0.000766,
      "conv_equity": 0.7916,
      "free": false
    },
    {
      "asset": "OP",
      "long_usd": 2814.95,
      "short_usd": 423214.8,
      "net_usd": -420399.85,
      "tilt": -0.9868,
      "position_count": 4,
      "long_count": 1,
      "short_count": 3,
      "L_net_margin": -4.933926,
      "L_net_equity": -0.000756,
      "conv_equity": -0.9919,
      "free": false
    },
    {
      "asset": "ICP",
      "long_usd": 419399.78,
      "short_usd": 16644.1,
      "net_usd": 402755.68,
      "tilt": 0.9237,
      "position_count": 2,
      "long_count": 1,
      "short_count": 1,
      "L_net_margin": 4.252827,
      "L_net_equity": 0.000725,
      "conv_equity": 0.8293,
      "free": false
    },
    {
      "asset": "ATOM",
      "long_usd": 323955.94,
      "short_usd": 47736.3,
      "net_usd": 276219.64,
      "tilt": 0.7431,
      "position_count": 4,
      "long_count": 3,
      "short_count": 1,
      "L_net_margin": 3.715704,
      "L_net_equity": 0.000497,
      "conv_equity": 0.7632,
      "free": false
    },
    {
      "asset": "PYTH",
      "long_usd": 0.0,
      "short_usd": 272567.12,
      "net_usd": -272567.12,
      "tilt": -1.0,
      "position_count": 1,
      "long_count": 0,
      "short_count": 1,
      "L_net_margin": -5.0,
      "L_net_equity": -0.00049,
      "conv_equity": -1.0,
      "free": false
    },
    {
      "asset": "ZK",
      "long_usd": 262940.51,
      "short_usd": 152.79,
      "net_usd": 262787.72,
      "tilt": 0.9988,
      "position_count": 2,
      "long_count": 1,
      "short_count": 1,
      "L_net_margin": 4.994193,
      "L_net_equity": 0.000473,
      "conv_equity": 0.9973,
      "free": false
    },
    {
      "asset": "ALGO",
      "long_usd": 257287.25,
      "short_usd": 0.0,
      "net_usd": 257287.25,
      "tilt": 1.0,
      "position_count": 1,
      "long_count": 1,
      "short_count": 0,
      "L_net_margin": 5.0,
      "L_net_equity": 0.000463,
      "conv_equity": 1.0,
      "free": false
    },
    {
      "asset": "ARB",
      "long_usd": 87987.24,
      "short_usd": 341796.46,
      "net_usd": -253809.22,
      "tilt": -0.5906,
      "position_count": 3,
      "long_count": 1,
      "short_count": 2,
      "L_net_margin": -5.905511,
      "L_net_equity": -0.000457,
      "conv_equity": -0.4374,
      "free": false
    },
    {
      "asset": "STBL",
      "long_usd": 73467.91,
      "short_usd": 301779.97,
      "net_usd": -228312.06,
      "tilt": -0.6084,
      "position_count": 6,
      "long_count": 1,
      "short_count": 5,
      "L_net_margin": -1.311677,
      "L_net_equity": -0.000411,
      "conv_equity": -0.7454,
      "free": false
    },
    {
      "asset": "LDO",
      "long_usd": 811805.12,
      "short_usd": 1016254.33,
      "net_usd": -204449.21,
      "tilt": -0.1118,
      "position_count": 4,
      "long_count": 2,
      "short_count": 2,
      "L_net_margin": -0.217967,
      "L_net_equity": -0.000368,
      "conv_equity": -0.18,
      "free": false
    },
    {
      "asset": "CRV",
      "long_usd": 303028.41,
      "short_usd": 497189.66,
      "net_usd": -194161.25,
      "tilt": -0.2426,
      "position_count": 5,
      "long_count": 2,
      "short_count": 3,
      "L_net_margin": -2.391337,
      "L_net_equity": -0.000349,
      "conv_equity": 0.1251,
      "free": false
    },
    {
      "asset": "ZRO",
      "long_usd": 3845973.03,
      "short_usd": 4018623.47,
      "net_usd": -172650.43,
      "tilt": -0.022,
      "position_count": 7,
      "long_count": 3,
      "short_count": 4,
      "L_net_margin": -0.107315,
      "L_net_equity": -0.000311,
      "conv_equity": 0.1679,
      "free": false
    },
    {
      "asset": "WLD",
      "long_usd": 1364403.29,
      "short_usd": 1525677.23,
      "net_usd": -161273.94,
      "tilt": -0.0558,
      "position_count": 6,
      "long_count": 2,
      "short_count": 4,
      "L_net_margin": -0.558026,
      "L_net_equity": -0.00029,
      "conv_equity": -0.1483,
      "free": false
    },
    {
      "asset": "BCH",
      "long_usd": 583552.32,
      "short_usd": 465119.86,
      "net_usd": 118432.46,
      "tilt": 0.1129,
      "position_count": 3,
      "long_count": 1,
      "short_count": 2,
      "L_net_margin": 1.129356,
      "L_net_equity": 0.000213,
      "conv_equity": 0.0912,
      "free": false
    },
    {
      "asset": "AZTEC",
      "long_usd": 604223.22,
      "short_usd": 721989.69,
      "net_usd": -117766.47,
      "tilt": -0.0888,
      "position_count": 5,
      "long_count": 2,
      "short_count": 3,
      "L_net_margin": -0.266397,
      "L_net_equity": -0.000212,
      "conv_equity": -0.1128,
      "free": false
    },
    {
      "asset": "FET",
      "long_usd": 177357.54,
      "short_usd": 278598.71,
      "net_usd": -101241.17,
      "tilt": -0.222,
      "position_count": 4,
      "long_count": 3,
      "short_count": 1,
      "L_net_margin": -1.110207,
      "L_net_equity": -0.000182,
      "conv_equity": 0.0313,
      "free": false
    },
    {
      "asset": "XMR",
      "long_usd": 4906630.57,
      "short_usd": 4973503.51,
      "net_usd": -66872.95,
      "tilt": -0.0068,
      "position_count": 10,
      "long_count": 4,
      "short_count": 6,
      "L_net_margin": -0.028251,
      "L_net_equity": -0.00012,
      "conv_equity": -0.3413,
      "free": false
    },
    {
      "asset": "ONDO",
      "long_usd": 721188.23,
      "short_usd": 669931.29,
      "net_usd": 51256.95,
      "tilt": 0.0368,
      "position_count": 4,
      "long_count": 1,
      "short_count": 3,
      "L_net_margin": 0.065032,
      "L_net_equity": 9.2e-05,
      "conv_equity": 0.3799,
      "free": false
    },
    {
      "asset": "BIO",
      "long_usd": 738916.2,
      "short_usd": 704019.89,
      "net_usd": 34896.31,
      "tilt": 0.0242,
      "position_count": 4,
      "long_count": 1,
      "short_count": 3,
      "L_net_margin": 0.035843,
      "L_net_equity": 6.3e-05,
      "conv_equity": 0.573,
      "free": false
    },
    {
      "asset": "LINK",
      "long_usd": 3525563.64,
      "short_usd": 3491743.25,
      "net_usd": 33820.4,
      "tilt": 0.0048,
      "position_count": 7,
      "long_count": 2,
      "short_count": 5,
      "L_net_margin": 0.048196,
      "L_net_equity": 6.1e-05,
      "conv_equity": -0.1552,
      "free": false
    },
    {
      "asset": "VIRTUAL",
      "long_usd": 1205135.45,
      "short_usd": 1238836.16,
      "net_usd": -33700.71,
      "tilt": -0.0138,
      "position_count": 6,
      "long_count": 2,
      "short_count": 4,
      "L_net_margin": -0.068947,
      "L_net_equity": -6.1e-05,
      "conv_equity": 0.3637,
      "free": false
    },
    {
      "asset": "STRK",
      "long_usd": 409669.15,
      "short_usd": 398629.05,
      "net_usd": 11040.1,
      "tilt": 0.0137,
      "position_count": 4,
      "long_count": 2,
      "short_count": 2,
      "L_net_margin": 0.068292,
      "L_net_equity": 2e-05,
      "conv_equity": -0.3024,
      "free": false
    }
  ],
  "wallet_distribution": [
    {
      "net_notional": 93221348.89,
      "long_notional": 93221348.89,
      "short_notional": 0.0,
      "equity": 40503968.97
    },
    {
      "net_notional": 93220000.0,
      "long_notional": 93220000.0,
      "short_notional": 0.0,
      "equity": 12190619.9
    },
    {
      "net_notional": -83963089.97,
      "long_notional": 1427664.37,
      "short_notional": 85390754.35,
      "equity": 33447094.36
    },
    {
      "net_notional": 79379156.38,
      "long_notional": 79379156.38,
      "short_notional": 0.0,
      "equity": 10651318.04
    },
    {
      "net_notional": 59183129.47,
      "long_notional": 59183129.47,
      "short_notional": 0.0,
      "equity": 13131722.07
    },
    {
      "net_notional": 56666400.0,
      "long_notional": 56666400.0,
      "short_notional": 0.0,
      "equity": 14676926.73
    },
    {
      "net_notional": -52330828.62,
      "long_notional": 39086.07,
      "short_notional": 52369914.69,
      "equity": 21041655.93
    },
    {
      "net_notional": -51318358.37,
      "long_notional": 2083592.11,
      "short_notional": 53401950.48,
      "equity": 44657970.35
    },
    {
      "net_notional": 49564466.98,
      "long_notional": 49564466.98,
      "short_notional": 0.0,
      "equity": 9303677.71
    },
    {
      "net_notional": -46123327.79,
      "long_notional": 0.0,
      "short_notional": 46123327.79,
      "equity": 11173235.29
    },
    {
      "net_notional": -44945657.53,
      "long_notional": 0.0,
      "short_notional": 44945657.53,
      "equity": 14862468.93
    },
    {
      "net_notional": 40508054.81,
      "long_notional": 40508054.81,
      "short_notional": 0.0,
      "equity": 13464232.65
    },
    {
      "net_notional": 38871654.75,
      "long_notional": 38871654.75,
      "short_notional": 0.0,
      "equity": 3622373.75
    },
    {
      "net_notional": 32629800.0,
      "long_notional": 32629800.0,
      "short_notional": 0.0,
      "equity": 4248198.65
    },
    {
      "net_notional": -28191789.32,
      "long_notional": 0.0,
      "short_notional": 28191789.32,
      "equity": 7669852.71
    },
    {
      "net_notional": -27687998.22,
      "long_notional": 1008075.69,
      "short_notional": 28696073.91,
      "equity": 29990575.7
    },
    {
      "net_notional": 26021523.03,
      "long_notional": 26021523.03,
      "short_notional": 0.0,
      "equity": 5976106.82
    },
    {
      "net_notional": -20030602.2,
      "long_notional": 1369236.48,
      "short_notional": 21399838.68,
      "equity": 11886621.78
    },
    {
      "net_notional": 18564565.8,
      "long_notional": 18564565.8,
      "short_notional": 0.0,
      "equity": 12176380.84
    },
    {
      "net_notional": -16949182.02,
      "long_notional": 4144270.04,
      "short_notional": 21093452.06,
      "equity": 12492034.76
    },
    {
      "net_notional": 16113415.53,
      "long_notional": 26860965.99,
      "short_notional": 10747550.46,
      "equity": 9491716.02
    },
    {
      "net_notional": 15669773.21,
      "long_notional": 15669773.21,
      "short_notional": 0.0,
      "equity": 2093416.83
    },
    {
      "net_notional": -13209699.8,
      "long_notional": 641008.89,
      "short_notional": 13850708.69,
      "equity": 5231773.5
    },
    {
      "net_notional": -12936026.64,
      "long_notional": 2161187.1,
      "short_notional": 15097213.74,
      "equity": 3454007.96
    },
    {
      "net_notional": 12233626.77,
      "long_notional": 12233626.77,
      "short_notional": 0.0,
      "equity": 9370985.67
    },
    {
      "net_notional": -11740213.95,
      "long_notional": 972280.44,
      "short_notional": 12712494.38,
      "equity": 8019489.98
    },
    {
      "net_notional": 11153335.04,
      "long_notional": 11153335.04,
      "short_notional": 0.0,
      "equity": 2878517.77
    },
    {
      "net_notional": 10673919.5,
      "long_notional": 10673920.44,
      "short_notional": 0.94,
      "equity": 1398725.04
    },
    {
      "net_notional": 10293120.0,
      "long_notional": 10293120.0,
      "short_notional": 0.0,
      "equity": 2222051.81
    },
    {
      "net_notional": -10074851.89,
      "long_notional": 0.0,
      "short_notional": 10074851.89,
      "equity": 1490788.67
    },
    {
      "net_notional": 9916764.35,
      "long_notional": 9916764.35,
      "short_notional": 0.0,
      "equity": 2191302.24
    },
    {
      "net_notional": -9495425.33,
      "long_notional": 686385.25,
      "short_notional": 10181810.58,
      "equity": 1734858.83
    },
    {
      "net_notional": 9475549.03,
      "long_notional": 11425762.74,
      "short_notional": 1950213.71,
      "equity": 2257179.85
    },
    {
      "net_notional": -9334415.08,
      "long_notional": 25010.0,
      "short_notional": 9359425.08,
      "equity": 885627.04
    },
    {
      "net_notional": -9023035.24,
      "long_notional": 0.0,
      "short_notional": 9023035.24,
      "equity": 1010196.83
    },
    {
      "net_notional": 8722938.0,
      "long_notional": 8722938.0,
      "short_notional": 0.0,
      "equity": 944479.41
    },
    {
      "net_notional": -8437930.54,
      "long_notional": 0.0,
      "short_notional": 8437930.54,
      "equity": 3024337.88
    },
    {
      "net_notional": 6885027.48,
      "long_notional": 6885027.48,
      "short_notional": 0.0,
      "equity": 5958786.42
    },
    {
      "net_notional": 6620434.06,
      "long_notional": 6620434.06,
      "short_notional": 0.0,
      "equity": 2160251.93
    },
    {
      "net_notional": -6601365.06,
      "long_notional": 4071347.21,
      "short_notional": 10672712.27,
      "equity": 8263305.53
    },
    {
      "net_notional": 6538280.51,
      "long_notional": 31318635.28,
      "short_notional": 24780354.77,
      "equity": 15102775.36
    },
    {
      "net_notional": 6466489.58,
      "long_notional": 6466489.58,
      "short_notional": 0.0,
      "equity": 8571295.71
    },
    {
      "net_notional": -6398201.58,
      "long_notional": 329606.45,
      "short_notional": 6727808.04,
      "equity": 3983041.52
    },
    {
      "net_notional": 6137428.47,
      "long_notional": 6137428.47,
      "short_notional": 0.0,
      "equity": 6193586.17
    },
    {
      "net_notional": 6059673.05,
      "long_notional": 6135903.05,
      "short_notional": 76230.0,
      "equity": 2551252.8
    },
    {
      "net_notional": 6047598.88,
      "long_notional": 6461108.52,
      "short_notional": 413509.63,
      "equity": 1887027.03
    },
    {
      "net_notional": -5927845.98,
      "long_notional": 0.0,
      "short_notional": 5927845.98,
      "equity": 824416.59
    },
    {
      "net_notional": -5790337.63,
      "long_notional": 0.0,
      "short_notional": 5790337.63,
      "equity": 424669.45
    },
    {
      "net_notional": 5390622.48,
      "long_notional": 11736706.72,
      "short_notional": 6346084.24,
      "equity": 4990295.16
    },
    {
      "net_notional": 5264851.15,
      "long_notional": 5264851.15,
      "short_notional": 0.0,
      "equity": 1345267.63
    },
    {
      "net_notional": 4824866.85,
      "long_notional": 4824866.85,
      "short_notional": 0.0,
      "equity": 3923742.98
    },
    {
      "net_notional": 4735509.4,
      "long_notional": 4735509.4,
      "short_notional": 0.0,
      "equity": 1911212.26
    },
    {
      "net_notional": -4353014.77,
      "long_notional": 0.0,
      "short_notional": 4353014.77,
      "equity": 975863.47
    },
    {
      "net_notional": -4249812.09,
      "long_notional": 0.0,
      "short_notional": 4249812.09,
      "equity": 355604.37
    },
    {
      "net_notional": 4111749.98,
      "long_notional": 6797127.9,
      "short_notional": 2685377.92,
      "equity": 6192069.29
    },
    {
      "net_notional": -3939699.5,
      "long_notional": 82485.6,
      "short_notional": 4022185.1,
      "equity": 1147576.75
    },
    {
      "net_notional": 3650015.5,
      "long_notional": 3650015.5,
      "short_notional": 0.0,
      "equity": 1442922.05
    },
    {
      "net_notional": 3568290.16,
      "long_notional": 53435939.19,
      "short_notional": 49867649.03,
      "equity": 19108653.76
    },
    {
      "net_notional": -2808853.85,
      "long_notional": 0.0,
      "short_notional": 2808853.85,
      "equity": 736783.17
    },
    {
      "net_notional": -2770206.51,
      "long_notional": 0.0,
      "short_notional": 2770206.51,
      "equity": 2835455.77
    },
    {
      "net_notional": -2574233.44,
      "long_notional": 0.0,
      "short_notional": 2574233.44,
      "equity": 559453.16
    },
    {
      "net_notional": -2320515.17,
      "long_notional": 0.0,
      "short_notional": 2320515.17,
      "equity": 679277.48
    },
    {
      "net_notional": -2078483.02,
      "long_notional": 0.0,
      "short_notional": 2078483.02,
      "equity": 1190819.64
    },
    {
      "net_notional": 1861439.84,
      "long_notional": 1861439.84,
      "short_notional": 0.0,
      "equity": 658036.19
    },
    {
      "net_notional": -1747950.0,
      "long_notional": 0.0,
      "short_notional": 1747950.0,
      "equity": 398754.55
    },
    {
      "net_notional": -1741500.0,
      "long_notional": 0.0,
      "short_notional": 1741500.0,
      "equity": 547136.39
    },
    {
      "net_notional": -1639724.73,
      "long_notional": 0.0,
      "short_notional": 1639724.73,
      "equity": 2704334.18
    },
    {
      "net_notional": -1428926.07,
      "long_notional": 248.84,
      "short_notional": 1429174.91,
      "equity": 3789012.89
    },
    {
      "net_notional": -1373114.2,
      "long_notional": 0.0,
      "short_notional": 1373114.2,
      "equity": 632774.62
    },
    {
      "net_notional": 1144745.27,
      "long_notional": 1144745.27,
      "short_notional": 0.0,
      "equity": 123374.18
    },
    {
      "net_notional": -1038844.42,
      "long_notional": 0.0,
      "short_notional": 1038844.42,
      "equity": 84241.48
    },
    {
      "net_notional": 932280.0,
      "long_notional": 932280.0,
      "short_notional": 0.0,
      "equity": 125370.2
    },
    {
      "net_notional": 877825.28,
      "long_notional": 877825.28,
      "short_notional": 0.0,
      "equity": 7349329.47
    },
    {
      "net_notional": 797904.58,
      "long_notional": 797904.58,
      "short_notional": 0.0,
      "equity": 3930434.07
    },
    {
      "net_notional": 738916.2,
      "long_notional": 738916.2,
      "short_notional": 0.0,
      "equity": 744141.75
    },
    {
      "net_notional": 718656.19,
      "long_notional": 718656.19,
      "short_notional": 0.0,
      "equity": 717191.22
    },
    {
      "net_notional": -695759.16,
      "long_notional": 0.0,
      "short_notional": 695759.16,
      "equity": 2000260.53
    },
    {
      "net_notional": -606599.43,
      "long_notional": 1013025.08,
      "short_notional": 1619624.51,
      "equity": 2222618.53
    },
    {
      "net_notional": 605609.55,
      "long_notional": 880615.16,
      "short_notional": 275005.61,
      "equity": 119968.5
    },
    {
      "net_notional": -428870.0,
      "long_notional": 0.0,
      "short_notional": 428870.0,
      "equity": 137211.45
    },
    {
      "net_notional": -423007.3,
      "long_notional": 0.0,
      "short_notional": 423007.3,
      "equity": 1382727.92
    },
    {
      "net_notional": -296227.48,
      "long_notional": 0.0,
      "short_notional": 296227.48,
      "equity": 113230.07
    },
    {
      "net_notional": 257287.25,
      "long_notional": 257287.25,
      "short_notional": 0.0,
      "equity": 4558075.08
    },
    {
      "net_notional": 250942.25,
      "long_notional": 297765.6,
      "short_notional": 46823.34,
      "equity": 113123.94
    },
    {
      "net_notional": 242853.0,
      "long_notional": 242853.0,
      "short_notional": 0.0,
      "equity": 380740.05
    },
    {
      "net_notional": -167022.99,
      "long_notional": 0.0,
      "short_notional": 167022.99,
      "equity": 23561.47
    },
    {
      "net_notional": -163045.0,
      "long_notional": 0.0,
      "short_notional": 163045.0,
      "equity": 35981.83
    },
    {
      "net_notional": 104151.41,
      "long_notional": 104151.41,
      "short_notional": 0.0,
      "equity": 1064404.02
    },
    {
      "net_notional": 35595.07,
      "long_notional": 49329.85,
      "short_notional": 13734.78,
      "equity": 148308.12
    },
    {
      "net_notional": -26112.0,
      "long_notional": 0.0,
      "short_notional": 26112.0,
      "equity": 4491.87
    },
    {
      "net_notional": -23361.07,
      "long_notional": 0.0,
      "short_notional": 23361.07,
      "equity": 7724.15
    },
    {
      "net_notional": 0.0,
      "long_notional": 0.0,
      "short_notional": 0.0,
      "equity": 10292925.0
    },
    {
      "net_notional": 0.0,
      "long_notional": 0.0,
      "short_notional": 0.0,
      "equity": 6631798.25
    },
    {
      "net_notional": 0.0,
      "long_notional": 0.0,
      "short_notional": 0.0,
      "equity": 0.0
    },
    {
      "net_notional": 0.0,
      "long_notional": 0.0,
      "short_notional": 0.0,
      "equity": 282654.32
    },
    {
      "net_notional": 0.0,
      "long_notional": 0.0,
      "short_notional": 0.0,
      "equity": 5182096.95
    },
    {
      "net_notional": 0.0,
      "long_notional": 0.0,
      "short_notional": 0.0,
      "equity": 1000000.0
    },
    {
      "net_notional": 0.0,
      "long_notional": 0.0,
      "short_notional": 0.0,
      "equity": 9929105.52
    },
    {
      "net_notional": 0.0,
      "long_notional": 0.0,
      "short_notional": 0.0,
      "equity": 48033.42
    },
    {
      "net_notional": 0.0,
      "long_notional": 0.0,
      "short_notional": 0.0,
      "equity": 161546.72
    }
  ]
}