{
  "generated_at": "2026-06-03T09:00:38.924849",
  "cohort_rebalanced_at": "2026-06-01",
  "index_score": -0.207775,
  "leverage_dampening": false,
  "cohort_stats": {
    "total_equity": 336347582.57,
    "total_wallets": 100,
    "active_wallets": 100,
    "gross_long_usd": 473182985.95,
    "gross_short_usd": 867531134.07,
    "net_usd": -394348148.12,
    "gross_notional_usd": 1340714120.02,
    "L_cohort_total": 3.9861
  },
  "assets": [
    {
      "asset": "ETH",
      "long_usd": 90540257.66,
      "short_usd": 217832395.03,
      "net_usd": -127292137.38,
      "tilt": -0.4128,
      "position_count": 44,
      "long_count": 9,
      "short_count": 35,
      "L_net_margin": -3.28603,
      "L_net_equity": -0.378454,
      "conv_equity": -0.3802,
      "free": true
    },
    {
      "asset": "HYPE",
      "long_usd": 176796501.5,
      "short_usd": 269045980.38,
      "net_usd": -92249478.87,
      "tilt": -0.2069,
      "position_count": 53,
      "long_count": 16,
      "short_count": 37,
      "L_net_margin": -1.246658,
      "L_net_equity": -0.274268,
      "conv_equity": -0.5079,
      "free": true
    },
    {
      "asset": "ZEC",
      "long_usd": 10665969.13,
      "short_usd": 47859102.6,
      "net_usd": -37193133.47,
      "tilt": -0.6355,
      "position_count": 25,
      "long_count": 5,
      "short_count": 20,
      "L_net_margin": -3.400705,
      "L_net_equity": -0.110579,
      "conv_equity": -0.5544,
      "free": true
    },
    {
      "asset": "BTC",
      "long_usd": 105364924.86,
      "short_usd": 141895676.76,
      "net_usd": -36530751.91,
      "tilt": -0.1477,
      "position_count": 43,
      "long_count": 15,
      "short_count": 28,
      "L_net_margin": -0.999399,
      "L_net_equity": -0.10861,
      "conv_equity": -0.2085,
      "free": true
    },
    {
      "asset": "NEAR",
      "long_usd": 5822644.3,
      "short_usd": 35266769.65,
      "net_usd": -29444125.35,
      "tilt": -0.7166,
      "position_count": 18,
      "long_count": 4,
      "short_count": 14,
      "L_net_margin": -7.165866,
      "L_net_equity": -0.087541,
      "conv_equity": -0.7002,
      "free": true
    },
    {
      "asset": "LIT",
      "long_usd": 4096089.49,
      "short_usd": 16710351.27,
      "net_usd": -12614261.78,
      "tilt": -0.6063,
      "position_count": 18,
      "long_count": 4,
      "short_count": 14,
      "L_net_margin": -2.276463,
      "L_net_equity": -0.037504,
      "conv_equity": -0.3487,
      "free": false
    },
    {
      "asset": "TON",
      "long_usd": 10563952.06,
      "short_usd": 19192287.07,
      "net_usd": -8628335.01,
      "tilt": -0.29,
      "position_count": 17,
      "long_count": 5,
      "short_count": 12,
      "L_net_margin": -0.821272,
      "L_net_equity": -0.025653,
      "conv_equity": -0.1178,
      "free": false
    },
    {
      "asset": "AVAX",
      "long_usd": 0.0,
      "short_usd": 8333527.12,
      "net_usd": -8333527.12,
      "tilt": -1.0,
      "position_count": 10,
      "long_count": 0,
      "short_count": 10,
      "L_net_margin": -9.456248,
      "L_net_equity": -0.024777,
      "conv_equity": -1.0,
      "free": false
    },
    {
      "asset": "SOL",
      "long_usd": 23656470.51,
      "short_usd": 17047439.57,
      "net_usd": 6609030.94,
      "tilt": 0.1624,
      "position_count": 26,
      "long_count": 11,
      "short_count": 15,
      "L_net_margin": 1.979281,
      "L_net_equity": 0.019649,
      "conv_equity": -0.0346,
      "free": false
    },
    {
      "asset": "AAVE",
      "long_usd": 6966463.8,
      "short_usd": 977414.72,
      "net_usd": 5989049.08,
      "tilt": 0.7539,
      "position_count": 9,
      "long_count": 5,
      "short_count": 4,
      "L_net_margin": 7.5392,
      "L_net_equity": 0.017806,
      "conv_equity": 0.7468,
      "free": false
    },
    {
      "asset": "TAO",
      "long_usd": 30539.26,
      "short_usd": 5813940.38,
      "net_usd": -5783401.13,
      "tilt": -0.9895,
      "position_count": 13,
      "long_count": 1,
      "short_count": 12,
      "L_net_margin": -4.947747,
      "L_net_equity": -0.017195,
      "conv_equity": -0.9931,
      "free": false
    },
    {
      "asset": "VVV",
      "long_usd": 344988.55,
      "short_usd": 5486423.89,
      "net_usd": -5141435.34,
      "tilt": -0.8817,
      "position_count": 12,
      "long_count": 2,
      "short_count": 10,
      "L_net_margin": -2.645038,
      "L_net_equity": -0.015286,
      "conv_equity": -0.8002,
      "free": false
    },
    {
      "asset": "FARTCOIN",
      "long_usd": 752679.89,
      "short_usd": 5332220.63,
      "net_usd": -4579540.74,
      "tilt": -0.7526,
      "position_count": 13,
      "long_count": 3,
      "short_count": 10,
      "L_net_margin": -5.019352,
      "L_net_equity": -0.013616,
      "conv_equity": -0.3473,
      "free": false
    },
    {
      "asset": "BNB",
      "long_usd": 558033.05,
      "short_usd": 5054246.1,
      "net_usd": -4496213.05,
      "tilt": -0.8011,
      "position_count": 11,
      "long_count": 2,
      "short_count": 9,
      "L_net_margin": -6.547811,
      "L_net_equity": -0.013368,
      "conv_equity": -0.909,
      "free": false
    },
    {
      "asset": "DOGE",
      "long_usd": 140007.7,
      "short_usd": 4359476.79,
      "net_usd": -4219469.09,
      "tilt": -0.9378,
      "position_count": 8,
      "long_count": 2,
      "short_count": 6,
      "L_net_margin": -9.377672,
      "L_net_equity": -0.012545,
      "conv_equity": -0.9144,
      "free": false
    },
    {
      "asset": "PUMP",
      "long_usd": 604424.39,
      "short_usd": 4437474.16,
      "net_usd": -3833049.77,
      "tilt": -0.7602,
      "position_count": 15,
      "long_count": 3,
      "short_count": 12,
      "L_net_margin": -5.506937,
      "L_net_equity": -0.011396,
      "conv_equity": -0.67,
      "free": false
    },
    {
      "asset": "XMR",
      "long_usd": 2994939.15,
      "short_usd": 6693214.78,
      "net_usd": -3698275.62,
      "tilt": -0.3817,
      "position_count": 9,
      "long_count": 4,
      "short_count": 5,
      "L_net_margin": -1.908659,
      "L_net_equity": -0.010995,
      "conv_equity": -0.2515,
      "free": false
    },
    {
      "asset": "WLD",
      "long_usd": 762559.61,
      "short_usd": 4440250.37,
      "net_usd": -3677690.76,
      "tilt": -0.7069,
      "position_count": 11,
      "long_count": 2,
      "short_count": 9,
      "L_net_margin": -4.817322,
      "L_net_equity": -0.010934,
      "conv_equity": -0.5541,
      "free": false
    },
    {
      "asset": "ZRO",
      "long_usd": 6639250.54,
      "short_usd": 2977605.21,
      "net_usd": 3661645.33,
      "tilt": 0.3808,
      "position_count": 13,
      "long_count": 5,
      "short_count": 8,
      "L_net_margin": 1.871565,
      "L_net_equity": 0.010886,
      "conv_equity": 0.5946,
      "free": false
    },
    {
      "asset": "ASTER",
      "long_usd": 2442168.09,
      "short_usd": 5433206.12,
      "net_usd": -2991038.03,
      "tilt": -0.3798,
      "position_count": 12,
      "long_count": 2,
      "short_count": 10,
      "L_net_margin": -1.424526,
      "L_net_equity": -0.008893,
      "conv_equity": -0.4903,
      "free": false
    },
    {
      "asset": "PAXG",
      "long_usd": 1458391.04,
      "short_usd": 4409053.67,
      "net_usd": -2950662.63,
      "tilt": -0.5029,
      "position_count": 7,
      "long_count": 1,
      "short_count": 6,
      "L_net_margin": -3.702854,
      "L_net_equity": -0.008773,
      "conv_equity": -0.8489,
      "free": false
    },
    {
      "asset": "FET",
      "long_usd": 0.0,
      "short_usd": 2578974.39,
      "net_usd": -2578974.39,
      "tilt": -1.0,
      "position_count": 5,
      "long_count": 0,
      "short_count": 5,
      "L_net_margin": -5.0,
      "L_net_equity": -0.007668,
      "conv_equity": -1.0,
      "free": false
    },
    {
      "asset": "XRP",
      "long_usd": 5885415.76,
      "short_usd": 8344643.1,
      "net_usd": -2459227.34,
      "tilt": -0.1728,
      "position_count": 16,
      "long_count": 6,
      "short_count": 10,
      "L_net_margin": -3.390419,
      "L_net_equity": -0.007312,
      "conv_equity": -0.6517,
      "free": false
    },
    {
      "asset": "MON",
      "long_usd": 0.02,
      "short_usd": 2430066.49,
      "net_usd": -2430066.47,
      "tilt": -1.0,
      "position_count": 10,
      "long_count": 1,
      "short_count": 9,
      "L_net_margin": -4.640339,
      "L_net_equity": -0.007225,
      "conv_equity": -1.0,
      "free": false
    },
    {
      "asset": "ENA",
      "long_usd": 599504.22,
      "short_usd": 2909518.97,
      "net_usd": -2310014.75,
      "tilt": -0.6583,
      "position_count": 11,
      "long_count": 4,
      "short_count": 7,
      "L_net_margin": -2.654017,
      "L_net_equity": -0.006868,
      "conv_equity": -0.6698,
      "free": false
    },
    {
      "asset": "XPL",
      "long_usd": 1378790.1,
      "short_usd": 3079451.73,
      "net_usd": -1700661.63,
      "tilt": -0.3815,
      "position_count": 10,
      "long_count": 3,
      "short_count": 7,
      "L_net_margin": -2.052518,
      "L_net_equity": -0.005056,
      "conv_equity": -0.0148,
      "free": false
    },
    {
      "asset": "IP",
      "long_usd": 1379627.24,
      "short_usd": 90306.83,
      "net_usd": 1289320.41,
      "tilt": 0.8771,
      "position_count": 6,
      "long_count": 2,
      "short_count": 4,
      "L_net_margin": 2.631384,
      "L_net_equity": 0.003833,
      "conv_equity": 0.9509,
      "free": false
    },
    {
      "asset": "CHIP",
      "long_usd": 416406.41,
      "short_usd": 1612612.22,
      "net_usd": -1196205.81,
      "tilt": -0.5895,
      "position_count": 5,
      "long_count": 1,
      "short_count": 4,
      "L_net_margin": -1.768647,
      "L_net_equity": -0.003556,
      "conv_equity": -0.4302,
      "free": false
    },
    {
      "asset": "ONDO",
      "long_usd": 2042857.27,
      "short_usd": 1044989.99,
      "net_usd": 997867.28,
      "tilt": 0.3232,
      "position_count": 8,
      "long_count": 3,
      "short_count": 5,
      "L_net_margin": 1.024038,
      "L_net_equity": 0.002967,
      "conv_equity": -0.0396,
      "free": false
    },
    {
      "asset": "LINK",
      "long_usd": 0.0,
      "short_usd": 824915.15,
      "net_usd": -824915.15,
      "tilt": -1.0,
      "position_count": 7,
      "long_count": 0,
      "short_count": 7,
      "L_net_margin": -10.0,
      "L_net_equity": -0.002453,
      "conv_equity": -1.0,
      "free": false
    },
    {
      "asset": "UNI",
      "long_usd": 0.0,
      "short_usd": 816097.35,
      "net_usd": -816097.35,
      "tilt": -1.0,
      "position_count": 8,
      "long_count": 0,
      "short_count": 8,
      "L_net_margin": -10.0,
      "L_net_equity": -0.002426,
      "conv_equity": -1.0,
      "free": false
    },
    {
      "asset": "KPEPE",
      "long_usd": 342.61,
      "short_usd": 762429.19,
      "net_usd": -762086.58,
      "tilt": -0.9991,
      "position_count": 4,
      "long_count": 1,
      "short_count": 3,
      "L_net_margin": -9.991017,
      "L_net_equity": -0.002266,
      "conv_equity": -0.9996,
      "free": false
    },
    {
      "asset": "MNT",
      "long_usd": 0.0,
      "short_usd": 709052.5,
      "net_usd": -709052.5,
      "tilt": -1.0,
      "position_count": 4,
      "long_count": 0,
      "short_count": 4,
      "L_net_margin": -4.976832,
      "L_net_equity": -0.002108,
      "conv_equity": -1.0,
      "free": false
    },
    {
      "asset": "DYDX",
      "long_usd": 822057.22,
      "short_usd": 118438.57,
      "net_usd": 703618.65,
      "tilt": 0.7481,
      "position_count": 2,
      "long_count": 1,
      "short_count": 1,
      "L_net_margin": 3.740679,
      "L_net_equity": 0.002092,
      "conv_equity": 0.7939,
      "free": false
    },
    {
      "asset": "AERO",
      "long_usd": 0.38,
      "short_usd": 611846.75,
      "net_usd": -611846.37,
      "tilt": -1.0,
      "position_count": 3,
      "long_count": 1,
      "short_count": 2,
      "L_net_margin": -2.999996,
      "L_net_equity": -0.001819,
      "conv_equity": -1.0,
      "free": false
    },
    {
      "asset": "PURR",
      "long_usd": 0.0,
      "short_usd": 514510.34,
      "net_usd": -514510.34,
      "tilt": -1.0,
      "position_count": 2,
      "long_count": 0,
      "short_count": 2,
      "L_net_margin": -3.0,
      "L_net_equity": -0.00153,
      "conv_equity": -1.0,
      "free": false
    },
    {
      "asset": "MEGA",
      "long_usd": 210550.04,
      "short_usd": 710668.76,
      "net_usd": -500118.72,
      "tilt": -0.5429,
      "position_count": 3,
      "long_count": 1,
      "short_count": 2,
      "L_net_margin": -1.628664,
      "L_net_equity": -0.001487,
      "conv_equity": -0.6418,
      "free": false
    },
    {
      "asset": "SUI",
      "long_usd": 99358.29,
      "short_usd": 581362.42,
      "net_usd": -482004.12,
      "tilt": -0.7081,
      "position_count": 8,
      "long_count": 5,
      "short_count": 3,
      "L_net_margin": -7.080791,
      "L_net_equity": -0.001433,
      "conv_equity": -0.7807,
      "free": false
    },
    {
      "asset": "TRX",
      "long_usd": 533994.25,
      "short_usd": 61165.28,
      "net_usd": 472828.97,
      "tilt": 0.7945,
      "position_count": 4,
      "long_count": 3,
      "short_count": 1,
      "L_net_margin": 7.944575,
      "L_net_equity": 0.001406,
      "conv_equity": 0.9022,
      "free": false
    },
    {
      "asset": "AZTEC",
      "long_usd": 281705.73,
      "short_usd": 740352.5,
      "net_usd": -458646.77,
      "tilt": -0.4487,
      "position_count": 5,
      "long_count": 1,
      "short_count": 4,
      "L_net_margin": -1.346245,
      "L_net_equity": -0.001364,
      "conv_equity": -0.2209,
      "free": false
    },
    {
      "asset": "FIL",
      "long_usd": 0.0,
      "short_usd": 449332.85,
      "net_usd": -449332.85,
      "tilt": -1.0,
      "position_count": 3,
      "long_count": 0,
      "short_count": 3,
      "L_net_margin": -5.0,
      "L_net_equity": -0.001336,
      "conv_equity": -1.0,
      "free": false
    },
    {
      "asset": "TRUMP",
      "long_usd": 194643.71,
      "short_usd": 631886.52,
      "net_usd": -437242.81,
      "tilt": -0.529,
      "position_count": 8,
      "long_count": 2,
      "short_count": 6,
      "L_net_margin": -5.282132,
      "L_net_equity": -0.0013,
      "conv_equity": -0.8047,
      "free": false
    },
    {
      "asset": "BIO",
      "long_usd": 443494.96,
      "short_usd": 8931.33,
      "net_usd": 434563.63,
      "tilt": 0.9605,
      "position_count": 3,
      "long_count": 2,
      "short_count": 1,
      "L_net_margin": 0.973613,
      "L_net_equity": 0.001292,
      "conv_equity": 0.9639,
      "free": false
    },
    {
      "asset": "APEX",
      "long_usd": 0.0,
      "short_usd": 420714.44,
      "net_usd": -420714.44,
      "tilt": -1.0,
      "position_count": 4,
      "long_count": 0,
      "short_count": 4,
      "L_net_margin": -3.0,
      "L_net_equity": -0.001251,
      "conv_equity": -1.0,
      "free": false
    },
    {
      "asset": "ETHFI",
      "long_usd": 558596.59,
      "short_usd": 139668.19,
      "net_usd": 418928.4,
      "tilt": 0.6,
      "position_count": 3,
      "long_count": 2,
      "short_count": 1,
      "L_net_margin": 2.999782,
      "L_net_equity": 0.001246,
      "conv_equity": 0.8215,
      "free": false
    },
    {
      "asset": "WIF",
      "long_usd": 53817.04,
      "short_usd": 439393.27,
      "net_usd": -385576.23,
      "tilt": -0.7818,
      "position_count": 4,
      "long_count": 1,
      "short_count": 3,
      "L_net_margin": -3.908842,
      "L_net_equity": -0.001146,
      "conv_equity": -0.8184,
      "free": false
    },
    {
      "asset": "PENDLE",
      "long_usd": 258338.95,
      "short_usd": 613683.41,
      "net_usd": -355344.46,
      "tilt": -0.4075,
      "position_count": 4,
      "long_count": 2,
      "short_count": 2,
      "L_net_margin": -1.99151,
      "L_net_equity": -0.001056,
      "conv_equity": -0.718,
      "free": false
    },
    {
      "asset": "LTC",
      "long_usd": 1545.8,
      "short_usd": 333964.23,
      "net_usd": -332418.43,
      "tilt": -0.9908,
      "position_count": 5,
      "long_count": 2,
      "short_count": 3,
      "L_net_margin": -9.907853,
      "L_net_equity": -0.000988,
      "conv_equity": -0.9978,
      "free": false
    },
    {
      "asset": "VIRTUAL",
      "long_usd": 34522.96,
      "short_usd": 352326.28,
      "net_usd": -317803.31,
      "tilt": -0.8215,
      "position_count": 5,
      "long_count": 1,
      "short_count": 4,
      "L_net_margin": -4.107586,
      "L_net_equity": -0.000945,
      "conv_equity": -0.9543,
      "free": false
    },
    {
      "asset": "DOT",
      "long_usd": 261537.36,
      "short_usd": 0.0,
      "net_usd": 261537.36,
      "tilt": 1.0,
      "position_count": 1,
      "long_count": 1,
      "short_count": 0,
      "L_net_margin": 10.0,
      "L_net_equity": 0.000778,
      "conv_equity": 1.0,
      "free": false
    },
    {
      "asset": "ATOM",
      "long_usd": 266729.34,
      "short_usd": 47074.56,
      "net_usd": 219654.78,
      "tilt": 0.7,
      "position_count": 2,
      "long_count": 1,
      "short_count": 1,
      "L_net_margin": 3.499873,
      "L_net_equity": 0.000653,
      "conv_equity": 0.6158,
      "free": false
    },
    {
      "asset": "WLFI",
      "long_usd": 993492.54,
      "short_usd": 1169245.77,
      "net_usd": -175753.23,
      "tilt": -0.0813,
      "position_count": 10,
      "long_count": 3,
      "short_count": 7,
      "L_net_margin": -0.212506,
      "L_net_equity": -0.000523,
      "conv_equity": -0.2776,
      "free": false
    },
    {
      "asset": "XLM",
      "long_usd": 288825.9,
      "short_usd": 127196.5,
      "net_usd": 161629.4,
      "tilt": 0.3885,
      "position_count": 4,
      "long_count": 2,
      "short_count": 2,
      "L_net_margin": 1.942556,
      "L_net_equity": 0.000481,
      "conv_equity": -0.2093,
      "free": false
    },
    {
      "asset": "OP",
      "long_usd": 283728.18,
      "short_usd": 140224.37,
      "net_usd": 143503.81,
      "tilt": 0.3385,
      "position_count": 5,
      "long_count": 2,
      "short_count": 3,
      "L_net_margin": 1.692451,
      "L_net_equity": 0.000427,
      "conv_equity": -0.3857,
      "free": false
    },
    {
      "asset": "APT",
      "long_usd": 668368.28,
      "short_usd": 545129.27,
      "net_usd": 123239.01,
      "tilt": 0.1016,
      "position_count": 6,
      "long_count": 4,
      "short_count": 2,
      "L_net_margin": 1.015569,
      "L_net_equity": 0.000366,
      "conv_equity": 0.3499,
      "free": false
    },
    {
      "asset": "RENDER",
      "long_usd": 368523.87,
      "short_usd": 245863.7,
      "net_usd": 122660.16,
      "tilt": 0.1996,
      "position_count": 3,
      "long_count": 1,
      "short_count": 2,
      "L_net_margin": 0.998231,
      "L_net_equity": 0.000365,
      "conv_equity": 0.5567,
      "free": false
    },
    {
      "asset": "ADA",
      "long_usd": 438190.98,
      "short_usd": 329870.74,
      "net_usd": 108320.24,
      "tilt": 0.141,
      "position_count": 6,
      "long_count": 2,
      "short_count": 4,
      "L_net_margin": 1.410306,
      "L_net_equity": 0.000322,
      "conv_equity": 0.1625,
      "free": false
    },
    {
      "asset": "LDO",
      "long_usd": 862814.07,
      "short_usd": 791373.16,
      "net_usd": 71440.91,
      "tilt": 0.0432,
      "position_count": 8,
      "long_count": 3,
      "short_count": 5,
      "L_net_margin": 0.092644,
      "L_net_equity": 0.000212,
      "conv_equity": -0.0249,
      "free": false
    },
    {
      "asset": "ALGO",
      "long_usd": 225108.73,
      "short_usd": 285238.45,
      "net_usd": -60129.72,
      "tilt": -0.1178,
      "position_count": 4,
      "long_count": 1,
      "short_count": 3,
      "L_net_margin": -0.589106,
      "L_net_equity": -0.000179,
      "conv_equity": -0.1906,
      "free": false
    },
    {
      "asset": "BCH",
      "long_usd": 260147.39,
      "short_usd": 303362.96,
      "net_usd": -43215.57,
      "tilt": -0.0767,
      "position_count": 4,
      "long_count": 1,
      "short_count": 3,
      "L_net_margin": -0.766899,
      "L_net_equity": -0.000128,
      "conv_equity": -0.6599,
      "free": false
    }
  ],
  "wallet_distribution": [
    {
      "net_notional": 101180587.7,
      "long_notional": 101180587.7,
      "short_notional": 0.0,
      "equity": 31954606.32
    },
    {
      "net_notional": -93720145.91,
      "long_notional": 0.0,
      "short_notional": 93720145.91,
      "equity": 31240048.64
    },
    {
      "net_notional": -86467431.03,
      "long_notional": 15776807.9,
      "short_notional": 102244238.92,
      "equity": 26697718.29
    },
    {
      "net_notional": 75048000.0,
      "long_notional": 75048000.0,
      "short_notional": 0.0,
      "equity": 5231597.84
    },
    {
      "net_notional": -56189558.38,
      "long_notional": 0.0,
      "short_notional": 56189558.38,
      "equity": 7487688.54
    },
    {
      "net_notional": -43240159.93,
      "long_notional": 56462.28,
      "short_notional": 43296622.21,
      "equity": 7379167.0
    },
    {
      "net_notional": 39383004.0,
      "long_notional": 39383004.0,
      "short_notional": 0.0,
      "equity": 2088864.43
    },
    {
      "net_notional": -35263897.5,
      "long_notional": 666853.92,
      "short_notional": 35930751.42,
      "equity": 8938697.14
    },
    {
      "net_notional": 32997150.0,
      "long_notional": 32997150.0,
      "short_notional": 0.0,
      "equity": 17737572.45
    },
    {
      "net_notional": -30083006.41,
      "long_notional": 18731621.45,
      "short_notional": 48814627.86,
      "equity": 7939208.51
    },
    {
      "net_notional": -29455143.42,
      "long_notional": 183431.63,
      "short_notional": 29638575.05,
      "equity": 8616804.64
    },
    {
      "net_notional": -25981732.92,
      "long_notional": 0.0,
      "short_notional": 25981732.92,
      "equity": 3325127.75
    },
    {
      "net_notional": -25759213.57,
      "long_notional": 0.0,
      "short_notional": 25759213.57,
      "equity": 13085529.23
    },
    {
      "net_notional": -24727656.73,
      "long_notional": 0.0,
      "short_notional": 24727656.73,
      "equity": 2089702.8
    },
    {
      "net_notional": 22837655.6,
      "long_notional": 22837655.6,
      "short_notional": 0.0,
      "equity": 5687038.3
    },
    {
      "net_notional": -22654985.36,
      "long_notional": 0.0,
      "short_notional": 22654985.36,
      "equity": 2195456.75
    },
    {
      "net_notional": -20177421.68,
      "long_notional": 1161446.35,
      "short_notional": 21338868.03,
      "equity": 4227311.1
    },
    {
      "net_notional": -19981412.88,
      "long_notional": 1490814.47,
      "short_notional": 21472227.35,
      "equity": 9029958.05
    },
    {
      "net_notional": -17968857.66,
      "long_notional": 0.0,
      "short_notional": 17968857.66,
      "equity": 3385832.02
    },
    {
      "net_notional": 17613600.0,
      "long_notional": 17613600.0,
      "short_notional": 0.0,
      "equity": 9459999.84
    },
    {
      "net_notional": -17114116.7,
      "long_notional": 77518.33,
      "short_notional": 17191635.03,
      "equity": 8600716.49
    },
    {
      "net_notional": 15065652.4,
      "long_notional": 15065652.4,
      "short_notional": 0.0,
      "equity": 8638398.17
    },
    {
      "net_notional": -13764910.61,
      "long_notional": 0.0,
      "short_notional": 13764910.61,
      "equity": 1232269.37
    },
    {
      "net_notional": -13195267.71,
      "long_notional": 5218709.99,
      "short_notional": 18413977.7,
      "equity": 2742725.41
    },
    {
      "net_notional": -12995661.08,
      "long_notional": 0.0,
      "short_notional": 12995661.08,
      "equity": 1338985.39
    },
    {
      "net_notional": -12747024.75,
      "long_notional": 0.0,
      "short_notional": 12747024.75,
      "equity": 791395.71
    },
    {
      "net_notional": -11576848.71,
      "long_notional": 2517851.29,
      "short_notional": 14094700.0,
      "equity": 916523.8
    },
    {
      "net_notional": 10621893.65,
      "long_notional": 34502873.44,
      "short_notional": 23880979.79,
      "equity": 13587720.13
    },
    {
      "net_notional": -9908730.0,
      "long_notional": 0.0,
      "short_notional": 9908730.0,
      "equity": 851791.15
    },
    {
      "net_notional": -9896882.39,
      "long_notional": 0.0,
      "short_notional": 9896882.39,
      "equity": 853302.48
    },
    {
      "net_notional": -9519076.11,
      "long_notional": 1071803.16,
      "short_notional": 10590879.27,
      "equity": 1166872.84
    },
    {
      "net_notional": 9483358.02,
      "long_notional": 9483358.02,
      "short_notional": 0.0,
      "equity": 1232679.85
    },
    {
      "net_notional": -9027424.46,
      "long_notional": 826187.0,
      "short_notional": 9853611.46,
      "equity": 1159782.55
    },
    {
      "net_notional": -9010018.1,
      "long_notional": 0.0,
      "short_notional": 9010018.1,
      "equity": 948576.49
    },
    {
      "net_notional": -8916839.37,
      "long_notional": 330355.98,
      "short_notional": 9247195.35,
      "equity": 943008.4
    },
    {
      "net_notional": -8379945.42,
      "long_notional": 0.0,
      "short_notional": 8379945.42,
      "equity": 925550.49
    },
    {
      "net_notional": 7941434.31,
      "long_notional": 7941434.31,
      "short_notional": 0.0,
      "equity": 785741.89
    },
    {
      "net_notional": -7739594.44,
      "long_notional": 0.0,
      "short_notional": 7739594.44,
      "equity": 1803536.41
    },
    {
      "net_notional": 7472688.69,
      "long_notional": 7472688.69,
      "short_notional": 0.0,
      "equity": 1536024.73
    },
    {
      "net_notional": 7313311.88,
      "long_notional": 7313312.63,
      "short_notional": 0.75,
      "equity": 1145441.15
    },
    {
      "net_notional": -7209762.87,
      "long_notional": 1872.63,
      "short_notional": 7211635.5,
      "equity": 764674.38
    },
    {
      "net_notional": -6843409.95,
      "long_notional": 0.0,
      "short_notional": 6843409.95,
      "equity": 688715.91
    },
    {
      "net_notional": -6418149.13,
      "long_notional": 0.0,
      "short_notional": 6418149.13,
      "equity": 628856.02
    },
    {
      "net_notional": 6020220.69,
      "long_notional": 6394974.71,
      "short_notional": 374754.01,
      "equity": 1320742.36
    },
    {
      "net_notional": -5449806.83,
      "long_notional": 0.0,
      "short_notional": 5449806.83,
      "equity": 1946914.38
    },
    {
      "net_notional": -5421371.66,
      "long_notional": 0.0,
      "short_notional": 5421371.66,
      "equity": 1916368.26
    },
    {
      "net_notional": 5287178.3,
      "long_notional": 5287178.3,
      "short_notional": 0.0,
      "equity": 470176.31
    },
    {
      "net_notional": 5191550.17,
      "long_notional": 5191550.17,
      "short_notional": 0.0,
      "equity": 5286997.51
    },
    {
      "net_notional": -5146401.14,
      "long_notional": 0.0,
      "short_notional": 5146401.14,
      "equity": 1404187.85
    },
    {
      "net_notional": -4917837.5,
      "long_notional": 0.0,
      "short_notional": 4917837.5,
      "equity": 1819589.9
    },
    {
      "net_notional": 4881794.85,
      "long_notional": 4881794.85,
      "short_notional": 0.0,
      "equity": 2471999.51
    },
    {
      "net_notional": -4689500.0,
      "long_notional": 0.0,
      "short_notional": 4689500.0,
      "equity": 1550133.24
    },
    {
      "net_notional": -4621971.0,
      "long_notional": 1274140.0,
      "short_notional": 5896111.0,
      "equity": 874494.17
    },
    {
      "net_notional": 4327001.0,
      "long_notional": 4327001.0,
      "short_notional": 0.0,
      "equity": 1275871.52
    },
    {
      "net_notional": -4285489.49,
      "long_notional": 0.0,
      "short_notional": 4285489.49,
      "equity": 560343.04
    },
    {
      "net_notional": -3879008.95,
      "long_notional": 0.0,
      "short_notional": 3879008.95,
      "equity": 435604.85
    },
    {
      "net_notional": -3776095.22,
      "long_notional": 0.0,
      "short_notional": 3776095.22,
      "equity": 586884.05
    },
    {
      "net_notional": -3657637.72,
      "long_notional": 0.0,
      "short_notional": 3657637.72,
      "equity": 370792.77
    },
    {
      "net_notional": 3644425.92,
      "long_notional": 3644425.92,
      "short_notional": 0.0,
      "equity": 652799.1
    },
    {
      "net_notional": 3277588.79,
      "long_notional": 3487589.85,
      "short_notional": 210001.05,
      "equity": 998831.13
    },
    {
      "net_notional": -3273902.82,
      "long_notional": 2087.28,
      "short_notional": 3275990.1,
      "equity": 643832.9
    },
    {
      "net_notional": -3168117.46,
      "long_notional": 0.0,
      "short_notional": 3168117.46,
      "equity": 375511.24
    },
    {
      "net_notional": -3128536.68,
      "long_notional": 0.0,
      "short_notional": 3128536.68,
      "equity": 1152861.75
    },
    {
      "net_notional": -2845664.95,
      "long_notional": 0.0,
      "short_notional": 2845664.95,
      "equity": 202036.61
    },
    {
      "net_notional": 2683688.72,
      "long_notional": 2683688.72,
      "short_notional": 0.0,
      "equity": 889690.13
    },
    {
      "net_notional": -2631293.77,
      "long_notional": 0.0,
      "short_notional": 2631293.77,
      "equity": 542580.82
    },
    {
      "net_notional": 2258143.58,
      "long_notional": 2258143.58,
      "short_notional": 0.0,
      "equity": 962314.29
    },
    {
      "net_notional": -2253597.18,
      "long_notional": 0.0,
      "short_notional": 2253597.18,
      "equity": 1024132.14
    },
    {
      "net_notional": -2244656.22,
      "long_notional": 0.0,
      "short_notional": 2244656.22,
      "equity": 1716741.22
    },
    {
      "net_notional": 2238135.35,
      "long_notional": 2238135.35,
      "short_notional": 0.0,
      "equity": 749330.95
    },
    {
      "net_notional": 2219570.08,
      "long_notional": 2476262.87,
      "short_notional": 256692.79,
      "equity": 1780169.99
    },
    {
      "net_notional": -2093811.45,
      "long_notional": 1067.65,
      "short_notional": 2094879.1,
      "equity": 366326.64
    },
    {
      "net_notional": 2084318.26,
      "long_notional": 2280223.25,
      "short_notional": 195904.99,
      "equity": 5208724.24
    },
    {
      "net_notional": -1988811.0,
      "long_notional": 0.0,
      "short_notional": 1988811.0,
      "equity": 136553.24
    },
    {
      "net_notional": -1743846.0,
      "long_notional": 0.0,
      "short_notional": 1743846.0,
      "equity": 136154.96
    },
    {
      "net_notional": -1698301.25,
      "long_notional": 0.0,
      "short_notional": 1698301.25,
      "equity": 244439.76
    },
    {
      "net_notional": -1604064.59,
      "long_notional": 3992721.85,
      "short_notional": 5596786.44,
      "equity": 925872.11
    },
    {
      "net_notional": -1360502.0,
      "long_notional": 0.0,
      "short_notional": 1360502.0,
      "equity": 9848902.05
    },
    {
      "net_notional": 1067012.7,
      "long_notional": 1067012.7,
      "short_notional": 0.0,
      "equity": 215627.6
    },
    {
      "net_notional": -1066926.5,
      "long_notional": 149594.18,
      "short_notional": 1216520.68,
      "equity": 245086.7
    },
    {
      "net_notional": -1004541.61,
      "long_notional": 0.0,
      "short_notional": 1004541.61,
      "equity": 515268.7
    },
    {
      "net_notional": -860807.77,
      "long_notional": 0.0,
      "short_notional": 860807.77,
      "equity": 99463.84
    },
    {
      "net_notional": -702620.88,
      "long_notional": 0.0,
      "short_notional": 702620.88,
      "equity": 50926.31
    },
    {
      "net_notional": -667178.84,
      "long_notional": 0.0,
      "short_notional": 667178.84,
      "equity": 535148.18
    },
    {
      "net_notional": -588319.72,
      "long_notional": 659334.12,
      "short_notional": 1247653.84,
      "equity": 571907.46
    },
    {
      "net_notional": 443298.8,
      "long_notional": 443298.8,
      "short_notional": 0.0,
      "equity": 445040.66
    },
    {
      "net_notional": 389398.89,
      "long_notional": 389398.89,
      "short_notional": 0.0,
      "equity": 67092.27
    },
    {
      "net_notional": -375284.4,
      "long_notional": 0.0,
      "short_notional": 375284.4,
      "equity": 1431392.3
    },
    {
      "net_notional": -354197.78,
      "long_notional": 0.0,
      "short_notional": 354197.78,
      "equity": 118128.53
    },
    {
      "net_notional": 307573.82,
      "long_notional": 877200.0,
      "short_notional": 569626.18,
      "equity": 278695.65
    },
    {
      "net_notional": -262668.0,
      "long_notional": 0.0,
      "short_notional": 262668.0,
      "equity": 36407.01
    },
    {
      "net_notional": 225108.73,
      "long_notional": 225108.73,
      "short_notional": 0.0,
      "equity": 4274518.71
    },
    {
      "net_notional": -107771.37,
      "long_notional": 0.0,
      "short_notional": 107771.37,
      "equity": 10493.31
    },
    {
      "net_notional": -46995.29,
      "long_notional": 0.0,
      "short_notional": 46995.29,
      "equity": 3898.52
    },
    {
      "net_notional": -670.83,
      "long_notional": 0.0,
      "short_notional": 670.83,
      "equity": 142.39
    },
    {
      "net_notional": 0.0,
      "long_notional": 0.0,
      "short_notional": 0.0,
      "equity": 0.0
    },
    {
      "net_notional": 0.0,
      "long_notional": 0.0,
      "short_notional": 0.0,
      "equity": 0.0
    },
    {
      "net_notional": 0.0,
      "long_notional": 0.0,
      "short_notional": 0.0,
      "equity": 5182096.95
    },
    {
      "net_notional": 0.0,
      "long_notional": 0.0,
      "short_notional": 0.0,
      "equity": 10292925.0
    },
    {
      "net_notional": 0.0,
      "long_notional": 0.0,
      "short_notional": 0.0,
      "equity": 43198.61
    }
  ]
}